muni_is_api/__init__.py
muni_is_api/client.py
muni_is_api/entities.py
muni_is_api/errors.py
muni_is_api/files_api.py
muni_is_api/log_config.py
muni_is_api/utils.py
muni_is_api-0.8.1.dist-info/LICENSE
muni_is_api-0.8.1.dist-info/WHEEL
muni_is_api-0.8.1.dist-info/METADATA
muni_is_api-0.8.1.dist-info/RECORD
