Metadata-Version: 2.1
Name: muni-is-api
Version: 0.8.1
Summary: Python wrapper for the IS MUNI API
Home-page: https://github.com/pestanko/py-is-muni-api
License: MIT
Keywords: api,muni,wrapper
Author: Peter Stanko
Author-email: peter.stanko0@gmail.com
Requires-Python: >=3.6,<4.0
Classifier: Intended Audience :: Developers
Classifier: License :: OSI Approved :: Apache Software License
Classifier: License :: OSI Approved :: MIT License
Classifier: Operating System :: OS Independent
Classifier: Programming Language :: Python :: 3
Classifier: Programming Language :: Python :: 3.6
Classifier: Programming Language :: Python :: 3.7
Classifier: Programming Language :: Python :: 3.8
Classifier: Topic :: Utilities
Requires-Dist: coloredlogs (>=10.0,<11.0)
Requires-Dist: defusedxml (>=0.6.0,<0.7.0)
Requires-Dist: lxml (>=4.4,<5.0)
Requires-Dist: requests (>=2.22,<3.0)
Project-URL: Repository, https://github.com/pestanko/py-is-muni-api
